carrier_api/__init__.py
carrier_api/api_connection_graphql.py
carrier_api/api_websocket.py
carrier_api/api_websocket_data_updater.py
carrier_api/config.py
carrier_api/const.py
carrier_api/energy.py
carrier_api/errors.py
carrier_api/profile.py
carrier_api/status.py
carrier_api/stub.py
carrier_api/system.py
carrier_api/util.py
carrier_api-2.8.13.dist-info/licenses/LICENSE
carrier_api-2.8.13.dist-info/METADATA
carrier_api-2.8.13.dist-info/WHEEL
carrier_api-2.8.13.dist-info/top_level.txt
carrier_api-2.8.13.dist-info/RECORD
