Metadata-Version: 2.4
Name: carrier_api
Version: 2.8.13
Summary: Carrier Api Wrapper
Author-email: Bren Dahl <dahl.brendan@gmail.com>
Project-URL: Homepage, https://github.com/dahlb/carrier_api
Project-URL: Bug Tracker, https://github.com/dahlb/carrier_api/issues
Keywords: carrier,api
Classifier: Development Status :: 4 - Beta
Classifier: License :: OSI Approved :: MIT License
Classifier: Natural Language :: English
Classifier: Intended Audience :: Developers
Classifier: Programming Language :: Python :: 3
Classifier: Operating System :: MacOS :: MacOS X
Requires-Python: <4,>=3.10
License-File: LICENSE
Requires-Dist: gql[aiohttp]
Requires-Dist: aiohttp
Requires-Dist: deepmerge
Requires-Dist: python-dateutil
Dynamic: license-file
